MANIFEST.in
README.rst
requirements.txt
setup.cfg
setup.py
bglogs/__init__.py
bglogs/configuration.py
bglogs/filter.py
bglogs/format.py
bglogs/logger.py
bglogs/messages.py
bglogs.egg-info/PKG-INFO
bglogs.egg-info/SOURCES.txt
bglogs.egg-info/dependency_links.txt
bglogs.egg-info/top_level.txt
tests/__init__.py
tests/test_get_logger.py
tests/test_logger_default.py
tests/test_messages.py