Metadata-Version: 1.0
Name: bglogs
Version: 0.6
Summary: BBGLab python logging with customized default formatting and behaviour
Home-page: https://bitbucket.org/bgframework/bglogs/get/0.6.tar.gz
Author: BBGLab
Author-email: bbglab@irbbarcelona.org
License: UNKNOWN
Platform: UNKNOWN
